codex_arch/__init__.py
codex_arch/analyzer.py
codex_arch/indexer.py
codex_arch/query.py
codex_arch/report.py
codex_arch/storage.py
codex_arch/api/__init__.py
codex_arch/api/app.py
codex_arch/api/config.py
codex_arch/api/docs.py
codex_arch/api/utils.py
codex_arch/api/auth/__init__.py
codex_arch/api/auth/token.py
codex_arch/api/cache/__init__.py
codex_arch/api/cache/stats.py
codex_arch/api/cache/utils.py
codex_arch/api/routes/__init__.py
codex_arch/api/routes/analysis.py
codex_arch/api/routes/artifacts.py
codex_arch/api/routes/auth.py
codex_arch/api/routes/info.py
codex_arch/bundler/__init__.py
codex_arch/bundler/context_bundle_assembler.py
codex_arch/change_detection/__init__.py
codex_arch/change_detection/caching.py
codex_arch/change_detection/git_changes.py
codex_arch/change_detection/incremental.py
codex_arch/change_detection/summary.py
codex_arch/cli/__init__.py
codex_arch/cli/analyze_cmd.py
codex_arch/cli/api_cmd.py
codex_arch/cli/bundle_cmd.py
codex_arch/cli/cli.py
codex_arch/cli/convert_deps_cmd.py
codex_arch/cli/dependency_cmd.py
codex_arch/cli/file_tree_cmd.py
codex_arch/cli/graph_cmd.py
codex_arch/cli/main.py
codex_arch/cli/metrics_cmd.py
codex_arch/cli/pipeline_cmd.py
codex_arch/cli/query_deps_cmd.py
codex_arch/cli/quick_examples.py
codex_arch/cli/run_all.py
codex_arch/cli/summary_cmd.py
codex_arch/cli/visualization_cmd.py
codex_arch/cli/commands/__init__.py
codex_arch/cli/commands/dependency_query.py
codex_arch/extractors/__init__.py
codex_arch/extractors/convert_deps.py
codex_arch/extractors/file_tree_extractor.py
codex_arch/extractors/find_deps.py
codex_arch/extractors/python/__init__.py
codex_arch/extractors/python/dependency_graph.py
codex_arch/extractors/python/extractor.py
codex_arch/extractors/python/import_parser.py
codex_arch/extractors/python/json_exporter.py
codex_arch/extractors/python/path_resolver.py
codex_arch/extractors/scripts/__init__.py
codex_arch/hooks/__init__.py
codex_arch/hooks/config.py
codex_arch/hooks/hook_scripts.py
codex_arch-1.0.1.dist-info/licenses/LICENSE
codex_arch-1.0.1.dist-info/METADATA
codex_arch-1.0.1.dist-info/WHEEL
codex_arch-1.0.1.dist-info/entry_points.txt
codex_arch-1.0.1.dist-info/top_level.txt
codex_arch-1.0.1.dist-info/RECORD
