Metadata-Version: 2.4
Name: codex-arch
Version: 1.0.1
Summary: A tool for analyzing and visualizing code architecture
Home-page: https://github.com/egouilliard/codex-arch
Author: Codex-Arch Team
Author-email: author@example.com
License: MIT
Classifier: Programming Language :: Python :: 3
Classifier: License :: OSI Approved :: MIT License
Classifier: Operating System :: OS Independent
Classifier: Development Status :: 3 - Alpha
Classifier: Intended Audience :: Developers
Classifier: Topic :: Software Development :: Libraries :: Python Modules
Requires-Python: >=3.7
License-File: LICENSE
Requires-Dist: pathlib
Requires-Dist: click>=8.0.0
Requires-Dist: graphviz>=0.20.0
Requires-Dist: tqdm>=4.66.0
Requires-Dist: Flask>=2.3.0
Requires-Dist: Flask-Cors>=4.0.0
Requires-Dist: GitPython>=3.1.40
Dynamic: author
Dynamic: author-email
Dynamic: home-page
Dynamic: license-file
Dynamic: requires-dist
Dynamic: requires-python
